{
    "diagnostic.errorSign": ">>",
    "diagnostic.warningSign": ">>",
    "diagnostic.infoSign": ">>",
    "powershell.integratedConsole.showOnStartup": false,
    "python.jediEnabled": false,
    "python.formatting.provider":"black",
    "python.linting.flake8Enabled": true,
    "python.linting.mypyEnabled": true,
    "python.linting.mypyArgs": [
        "--no-pretty",
        "--ignore-missing-imports",
        "--follow-imports=silent",
        "--show-column-numbers",
        "--disallow-untyped-calls",
        "--disallow-untyped-defs",
        "--disallow-incomplete-defs",
        "--check-untyped-defs"
    ],
    "yaml.customTags": [
        "!Base64",
        "!Base64 mapping",
        "!Cidr sequence",
        "!And sequence",
        "!Equals sequence",
        "!If sequence",
        "!Not sequence",
        "!Or sequence",
        "!Condition",
        "!FindInMap sequence",
        "!GetAtt",
        "!GetAtt sequence",
        "!GetAZs",
        "!ImportValue",
        "!Join sequence",
        "!Select sequence",
        "!Split sequence",
        "!Sub",
        "!Sub sequence",
        "!Transform mapping",
        "!Ref"
    ]
}
